
{
    "id": 1,
    "title": "Summer Art Camp! 5 Days of Artists and Painting Monet, Van Gogh, Matisse, & More",
    "content": "in this 5 day class we explore artists Monet, Matisse, Van Gogh, among others ad then recreate paintings using crayon and watercolor. Students will have fun learning about the arists & creating their own art inspired by their work.",
    "user_img": " https://images.pexels.com/photos/4350178/pexels-photo-4350178.jpeg?auto=compress&cs=tinysrgb&dpr=2&h=650&w=940",
    "user-name": "Kimberly R Mosler",
    "star": "⭐⭐⭐⭐⭐ ",
    "review1": "467 total reviews for this teacher",
    "review2": "5 reviews for this class",
    "total_reviews": "Completed by 21 learners",
    "main_img": "/img3.jpg"
  }
  